gempaterkini/__init__.py
BMKG_earthquake_update-0.0.1.dist-info/LICENSE
BMKG_earthquake_update-0.0.1.dist-info/METADATA
BMKG_earthquake_update-0.0.1.dist-info/WHEEL
BMKG_earthquake_update-0.0.1.dist-info/top_level.txt
BMKG_earthquake_update-0.0.1.dist-info/RECORD
