Metadata-Version: 2.1
Name: BMKG-earthquake-update
Version: 0.0.1
Summary: this package will get the latest earthquake from BMKG -Meteorology, Climatology, and Geophysics Agency
Author-email: ahmad sopyan <madsopyan5@gmail.com>
Project-URL: Homepage, https://github.com/madshopy/latest-indonesia-earthquake/tree/main
Classifier: Programming Language :: Python :: 3
Classifier: License :: OSI Approved :: GNU General Public License v3 (GPLv3)
Classifier: Operating System :: OS Independent
Requires-Python: >=3.13
License-File: LICENSE
